iptvpy/IPTV.py
iptvpy/MacPortal.py
iptvpy/__init__.py
iptvpy-2.0.1.dist-info/licenses/LICENSE
iptvpy-2.0.1.dist-info/METADATA
iptvpy-2.0.1.dist-info/WHEEL
iptvpy-2.0.1.dist-info/top_level.txt
iptvpy-2.0.1.dist-info/RECORD
