Metadata-Version: 2.4
Name: iptvpy
Version: 2.0.1
Summary: A modular Python library for IPTV portal interaction.
Author: भाग्य ज्योति (Bhagya Jyoti)
License: Apache License Version 2.0
Project-URL: Homepage, https://github.com/BhagyaJyoti22006/iptvpy
Project-URL: Repository, https://github.com/BhagyaJyoti22006/iptvpy
Project-URL: Issues, https://github.com/BhagyaJyoti22006/iptvpy/issues
Keywords: iptv,macportal,stalker,ministra,portal,handshake,live,catchup,vod,series,epg,download
Classifier: Programming Language :: Python :: 3
Classifier: License :: OSI Approved :: Apache Software License
Classifier: Operating System :: OS Independent
Classifier: Intended Audience :: Developers
Classifier: Topic :: Internet :: WWW/HTTP
Classifier: Topic :: Software Development :: Libraries :: Python Modules
Classifier: Development Status :: 5 - Production/Stable
Requires-Python: >=3.7
License-File: LICENSE
Requires-Dist: cloudscraper>=1.2.71
Dynamic: license-file
